Metadata-Version: 2.1
Name: django-revproxy-verteva
Version: 0.10.0
Summary: Yet another Django reverse proxy application.
Home-page: https://github.com/TracyWebTech/django-revproxy
Author: Sergio Oliveira
Author-email: sergio@tracy.com.br
License: MPL v2.0
Platform: UNKNOWN
Classifier: Development Status :: 5 - Production/Stable
Classifier: Environment :: Web Environment
Classifier: Framework :: Django
Classifier: Intended Audience :: Developers
Classifier: License :: OSI Approved :: Mozilla Public License 2.0 (MPL 2.0)
Classifier: Operating System :: OS Independent
Classifier: Programming Language :: Python
Classifier: Programming Language :: Python :: 2.7
Classifier: Programming Language :: Python :: 3.5
Classifier: Programming Language :: Python :: 3.6
Classifier: Programming Language :: Python :: 3.7
Classifier: Programming Language :: Python :: 3.8
Classifier: Programming Language :: Python :: Implementation :: CPython
Classifier: Programming Language :: Python :: Implementation :: PyPy
Classifier: Topic :: Internet :: Proxy Servers
Classifier: Topic :: Internet :: WWW/HTTP
Classifier: Topic :: Software Development :: Libraries
License-File: LICENSE
Requires-Dist: django (>=1.7)
Requires-Dist: urllib3 (>=1.12)
Provides-Extra: diazo
Requires-Dist: diazo (>=1.0.5) ; extra == 'diazo'
Requires-Dist: lxml (>=3.4) ; extra == 'diazo'
